pythondata_misc_tapcfg/__init__.py
pythondata_misc_tapcfg/data/.arcconfig
pythondata_misc_tapcfg/data/COPYING
pythondata_misc_tapcfg/data/ChangeLog
pythondata_misc_tapcfg/data/README
pythondata_misc_tapcfg/data/SConstruct
pythondata_misc_tapcfg/data/buildall.sh
pythondata_misc_tapcfg/data/drivers/README
pythondata_misc_tapcfg/data/drivers/osx/tuntap/Changelog
pythondata_misc_tapcfg/data/drivers/osx/tuntap/INSTALL
pythondata_misc_tapcfg/data/drivers/osx/tuntap/Makefile
pythondata_misc_tapcfg/data/drivers/osx/tuntap/README
pythondata_misc_tapcfg/data/drivers/osx/tuntap/README.installer
pythondata_misc_tapcfg/data/drivers/osx/tuntap/pkg/res/License.rtfd/TXT.rtf
pythondata_misc_tapcfg/data/drivers/osx/tuntap/pkg/res/Welcome.rtfd/TXT.rtf
pythondata_misc_tapcfg/data/drivers/osx/tuntap/pkg/res/Welcome.rtfd/paypal_button.gif
pythondata_misc_tapcfg/data/drivers/osx/tuntap/pkg/scripts/startup_item_tap/postflight
pythondata_misc_tapcfg/data/drivers/osx/tuntap/pkg/scripts/startup_item_tun/postflight
pythondata_misc_tapcfg/data/drivers/osx/tuntap/pkg/scripts/tap/postflight
pythondata_misc_tapcfg/data/drivers/osx/tuntap/pkg/scripts/tun/postflight
pythondata_misc_tapcfg/data/drivers/osx/tuntap/pkg/tuntap.pmdoc/01tun-contents.xml
pythondata_misc_tapcfg/data/drivers/osx/tuntap/pkg/tuntap.pmdoc/01tun.xml
pythondata_misc_tapcfg/data/drivers/osx/tuntap/pkg/tuntap.pmdoc/02tap-contents.xml
pythondata_misc_tapcfg/data/drivers/osx/tuntap/pkg/tuntap.pmdoc/02tap.xml
pythondata_misc_tapcfg/data/drivers/osx/tuntap/pkg/tuntap.pmdoc/03tap-contents.xml
pythondata_misc_tapcfg/data/drivers/osx/tuntap/pkg/tuntap.pmdoc/03tap.xml
pythondata_misc_tapcfg/data/drivers/osx/tuntap/pkg/tuntap.pmdoc/04tun-contents.xml
pythondata_misc_tapcfg/data/drivers/osx/tuntap/pkg/tuntap.pmdoc/04tun.xml
pythondata_misc_tapcfg/data/drivers/osx/tuntap/pkg/tuntap.pmdoc/index.xml
pythondata_misc_tapcfg/data/drivers/osx/tuntap/src/ifaddr.h
pythondata_misc_tapcfg/data/drivers/osx/tuntap/src/lock.cc
pythondata_misc_tapcfg-0.0.post517.dist-info/LICENSE
pythondata_misc_tapcfg-0.0.post517.dist-info/METADATA
pythondata_misc_tapcfg-0.0.post517.dist-info/WHEEL
pythondata_misc_tapcfg-0.0.post517.dist-info/top_level.txt
pythondata_misc_tapcfg-0.0.post517.dist-info/RECORD
