Metadata-Version: 2.1
Name: pythondata-misc-tapcfg
Version: 0.0.post517
Summary: Python module containing data files for Ethernet TAP Config misc.
Home-page: https://github.com/litex-hub/pythondata-misc-tapcfg
Author: LiteX Authors
Author-email: litex@googlegroups.com
Project-URL: Bug Tracker, https://github.com/litex-hub/pythondata-misc-tapcfg/issues
Project-URL: Source Code, https://github.com/litex-hub/pythondata-misc-tapcfg
Classifier: Programming Language :: Python :: 3
Classifier: License :: OSI Approved :: GNU Lesser General Public License v2 (LGPLv2)
Classifier: Operating System :: OS Independent
Requires-Python: >=3.5
License-File: LICENSE
